fastjson_db/__init__.py
fastjson_db/foreignkey.py
fastjson_db/jsonquerier.py
fastjson_db/jsontable.py
fastjson_db/jsonuniquer.py
fastjson_db/model.py
fastjson_db/datatypes/hashed.py
fastjson_db/datatypes/serializer.py
fastjson_db/datatypes/unique.py
fastjson_db/errors/FastJsonDBerror.py
fastjson_db/errors/datatype_error.py
fastjson_db/errors/model_table_errors.py
fastjson_db/errors/query_error.py
fastjson_db/errors/relationship_error.py
fastjson_db-0.3.5.dist-info/licenses/LICENSE
fastjson_db-0.3.5.dist-info/METADATA
fastjson_db-0.3.5.dist-info/WHEEL
fastjson_db-0.3.5.dist-info/top_level.txt
fastjson_db-0.3.5.dist-info/RECORD
