Metadata-Version: 2.4
Name: fastjson-db
Version: 0.3.5
Summary: A lightweight JSON database with dataclass support.
Author-email: Maurício Reisdoefer <mauricio.reisdoefer2009@gmail.com>
License: MIT License
Project-URL: Homepage, https://github.com/MauricioReisdoefer/fastjson-db
Project-URL: Bug Tracker, https://github.com/MauricioReisdoefer/fastjson-db/issues
Requires-Python: >=3.9
License-File: LICENSE
Provides-Extra: perf
Requires-Dist: orjson>=3.0; extra == "perf"
Dynamic: license-file
